setup.py
initool/__init__.py
initool.egg-info/PKG-INFO
initool.egg-info/SOURCES.txt
initool.egg-info/dependency_links.txt
initool.egg-info/entry_points.txt
initool.egg-info/top_level.txt