Metadata-Version: 1.1
Name: initool
Version: 0.1
Summary: INI files manipulator (get/set/remove) options and sections
Home-page: https://github.com/xmonader/initool
Author: Ahmed T. Youssef
Author-email: xmonader@gmail.com
License: BSD 3-Clause License
Platform: UNKNOWN
Classifier: Development Status :: 4 - Beta
Classifier: Environment :: Console
Classifier: Intended Audience :: Developers
Classifier: Intended Audience :: System Administrators
Classifier: License :: OSI Approved :: BSD License
Classifier: Operating System :: MacOS :: MacOS X
Classifier: Operating System :: Microsoft :: Windows
Classifier: Operating System :: POSIX
Classifier: Programming Language :: Python
